{
  "capes": [
    {
      "id": "AngelCape",
      "name": "Capa Angel",
      "file": "capes/AngelCape.png",
      "premium": false
    },
    {
      "id": "CreeperYellow",
      "name": "Kitty x Creeper",
      "file": "capes/Creeperxkitty.png",
      "premium": false
    },
    {
      "id": "SamuelPlayerCape",
      "name": "SamuelPl4yer Cape",
      "file": "capes/Samuel.png",
      "premium": false
    },
    {
      "id": "JesusCape",
      "name": "Jesus Cape",
      "file": "capes/JesusCape.png",
      "premium": false
    },
    {
      "id": "KowCape",
      "name": "Kow Cape",
      "file": "capes/KowCape.png",
      "allowedPlayers": [
        "wDreamx",
        "BGZINGAMER",
        "p_ofc"
      ]
    },
    {
      "id": "BlackAngel",
      "name": "Black Angel",
      "file": "capes/AngelBlack.png",
      "premium": false
    },
    {
      "id": "pinguincape",
      "name": "Pengu Ice",
      "file": "capes/pinguincape.png",
      "premium": false
    },
    {
      "id": "pintocape",
      "name": "Pinto Cape",
      "file": "capes/pintocape.png",
      "premium": false
    },
    {
      "id": "pintoblackcape",
      "name": "Black Pinto",
      "file": "capes/pintoblackcape.png",
      "premium": false
    },
    {
      "id": "PomboCape",
      "name": "Pombo Cape",
      "file": "capes/shimishimieicape.png",
      "allowedPlayers": [
        "8a391411-9263-4364-a1e6-b3e9408c9b0e",
        "BGZINGAMER"
      ]
    },
    {
      "id": "bgcape",
      "name": "Bgzin Cape",
      "file": "capes/bgcape.png",
      "premium": false
    },
    {
      "id": "nyancat",
      "name": "Nyan Cape",
      "file": "capes/nyancat.png",
      "premium": false
    },
    {
      "id": "capekitty",
      "name": "Kitty Cape",
      "file": "capes/Capekitty.png",
      "premium": false
    },
    {
      "id": "spydercape1",
      "name": "Spyder Cape",
      "file": "capes/spydercape1.png",
      "premium": false
    },
    {
      "id": "McLarenMP4",
      "name": "MP4 Cape",
      "file": "capes/McLarenMP4.png",
      "premium": false
    },
    {
      "id": "SennaHelmet",
      "name": "Senna Helmet",
      "file": "capes/SennaHelmet.png",
      "premium": false
    },
    {
      "id": "Tyrone",
      "name": "Tyrone Cape",
      "file": "capes/Tyrone.png",
      "allowedPlayers": [
        "8a391411-9263-4364-a1e6-b3e9408c9b0e",
        "S4muelPlayer"
      ]
    },
    {
      "id": "taboocape",
      "name": "Taboo Cape",
      "file": "capes/taboocape.png",
      "premium": false
    },
    {
      "id": "nadercape",
      "name": "Nader Cape",
      "file": "capes/nadercape.png",
      "premium": false
    },
    {
      "id": "nerfadocape",
      "name": "Nerfado Cape",
      "file": "capes/nerfardo.png",
      "premium": false
    },
     {
      "id": "lenom",
      "name": "Lenom Cape",
      "file": "capes/lenom.png",
      "premium": false
    },
     {
      "id": "deckk",
      "name": "Deck Cape",
      "file": "capes/deckk.png",
      "premium": false
    },
     {
      "id": "pjv",
      "name": "PJV Cape",
      "file": "capes/pjv.png",
      "premium": false
    },
     {
      "id": "witer",
      "name": "Wither Cape",
      "file": "capes/witercape.png",
      "premium": false
    },
     {
      "id": "oleugincape",
      "name": "Leguin Cape",
      "file": "capes/oleugimCape.png",
      "allowedPlayers": [
        "oleugim"
      ]
    },
     {
      "id": "thzincape",
      "name": "THZIN Cape",
      "file": "capes/thzin.png",
      "premium": false
    },
    {
      "id": "niclzz8",
      "name": "Make your game",
      "file": "capes/niclzz8.png",
      "premium": false
    },
  ]
}
